Reportom/__init__.py
Reportom/css.py
Reportom/html.py
Reportom/java.py
Reportom/report.py
reportom-0.0.3.dist-info/METADATA
reportom-0.0.3.dist-info/WHEEL
reportom-0.0.3.dist-info/licenses/LICENCE.txt
reportom-0.0.3.dist-info/RECORD
