Metadata-Version: 2.1
Name: Reportom
Version: 0.0.3
Summary: Help produce html code for reports
Author: Tom Bloem
License-File: LICENCE.txt
Classifier: License :: OSI Approved :: GNU General Public License v3 (GPLv3)
Classifier: Operating System :: OS Independent
Classifier: Programming Language :: Python :: 3
Requires-Python: >=3.7
